py_fumen_py/__init__.py
py_fumen_py/action.py
py_fumen_py/comment.py
py_fumen_py/constant.py
py_fumen_py/field.py
py_fumen_py/fumen_buffer.py
py_fumen_py/fumen_codec.py
py_fumen_py/js_escape.py
py_fumen_py/operation.py
py_fumen_py/page.py
py_fumen_py/quiz.py
py_fumen_py-0.0.10.dist-info/METADATA
py_fumen_py-0.0.10.dist-info/WHEEL
py_fumen_py-0.0.10.dist-info/licenses/LICENSE
py_fumen_py-0.0.10.dist-info/RECORD
