Metadata-Version: 2.1
Name: py_fumen_py
Version: 0.0.10
Summary: Python implementation of the JavaScript package 'tetris-fumen'
Project-URL: Source, https://github.com/OctupusTea/py-fumen-py
Author: Octupus Tea
License-File: LICENSE
Classifier: License :: OSI Approved :: MIT License
Classifier: Operating System :: OS Independent
Classifier: Programming Language :: Python :: 3
Requires-Python: >=3.8
